LICENSE
beanita/__init__.py
beanita/client.py
beanita/collection.py
beanita/cursor.py
beanita/db.py
beanita/results.py
beanita-0.1.0.dist-info/LICENSE
beanita-0.1.0.dist-info/WHEEL
beanita-0.1.0.dist-info/METADATA
beanita-0.1.0.dist-info/RECORD
