Metadata-Version: 2.1
Name: beanita
Version: 0.1.0
Summary: Local MongoDB-like database, based on Mongita and prepared to work with Beanie ODM
Home-page: https://github.com/roman-right/beanita
License: MIT
Author: Roman Right
Author-email: roman-right@protonmail.com
Requires-Python: >=3.9,<4.0
Classifier: License :: OSI Approved :: MIT License
Classifier: Programming Language :: Python :: 3
Classifier: Programming Language :: Python :: 3.9
Requires-Dist: mongita (>=1.1.1,<2.0.0)
Project-URL: Repository, https://github.com/roman-right/beanita
